{"story": "Narendra Modi added 5 new photos.", "from": {"name": "Narendra Modi", "id": "177526890164"}, "actions": [{"link": "https://www.facebook.com/narendramodi/posts/10156556166595165", "name": "Like"}, {"link": "https://www.facebook.com/narendramodi/posts/10156556166595165", "name": "Comment"}, {"link": "https://www.facebook.com/narendramodi/posts/10156556166595165", "name": "Share"}], "updated_time": "2017-06-03T11:11:22+0000", "full_picture": "https://scontent.xx.fbcdn.net/v/t1.0-9/s720x720/1937080_10156556153510165_3730207518070522027_n.jpg?oh=527ae49e6119ff69bcac8ad430dcce37&oe=59CB7FA4", "link": "https://www.facebook.com/narendramodi/photos/a.10150164299700165.421791.177526890164/10156556153510165/?type=3", "story_tags": [{"length": 13, "offset": 0, "type": "page", "id": "177526890164", "name": "Narendra Modi"}], "created_time": "2016-01-22T13:48:01+0000", "message": "Some pictures from the Ambedkar Mahasabha, Lucknow.", "type": "photo", "id": "177526890164_10156556166595165", "status_type": "added_photos"}