{"from": {"name": "Narendra Modi", "id": "177526890164"}, "actions": [{"link": "https://www.facebook.com/narendramodi/posts/10158937402200165:0", "name": "Like"}, {"link": "https://www.facebook.com/narendramodi/posts/10158937402200165:0", "name": "Comment"}, {"link": "https://www.facebook.com/narendramodi/posts/10158937402200165:0", "name": "Share"}], "updated_time": "2017-07-02T14:48:32+0000", "full_picture": "https://scontent.xx.fbcdn.net/v/t1.0-9/s720x720/19225686_10158937402200165_395055871267107755_n.jpg?oh=afa0845a69174497d87d577b9fa3dd00&oe=59C6880E", "link": "https://www.facebook.com/narendramodi/photos/a.10150164299700165.421791.177526890164/10158937402200165/?type=3", "created_time": "2017-06-18T14:37:39+0000", "message": "The demise of Swami Atmasthananda ji is a personal loss for me. \u202aI lived with him during a very important period of my life. \n\nSwami Atmasthananda ji was blessed with immense knowledge & wisdom. Generations will remember his exemplary personality.", "type": "photo", "id": "177526890164_10158937402200165", "status_type": "added_photos"}