{"from": {"name": "Narendra Modi", "id": "177526890164"}, "actions": [{"link": "https://www.facebook.com/narendramodi/posts/10156588043725165:0", "name": "Like"}, {"link": "https://www.facebook.com/narendramodi/posts/10156588043725165:0", "name": "Comment"}, {"link": "https://www.facebook.com/narendramodi/posts/10156588043725165:0", "name": "Share"}], "updated_time": "2017-01-26T09:07:56+0000", "full_picture": "https://scontent.xx.fbcdn.net/v/t1.0-9/12651169_10156588043725165_4795319350261000856_n.jpg?oh=1662e5826e7497b313199b7ea6ad8ac5&oe=5A058E5C", "link": "https://www.facebook.com/narendramodi/photos/a.10150164299700165.421791.177526890164/10156588043725165/?type=3", "created_time": "2016-02-01T08:33:31+0000", "message": "Greetings to all ranks of Indian Coast Guard on their Raising Day. Their relentless service on our maritime frontiers is exemplary. From guarding coasts, saving lives at sea & preventing marine pollution, we are proud of our Coast Guard personnel.", "type": "photo", "id": "177526890164_10156588043725165", "status_type": "added_photos"}