{"from": {"name": "Narendra Modi", "id": "177526890164"}, "actions": [{"link": "https://www.facebook.com/narendramodi/posts/10157222470805165:0", "name": "Like"}, {"link": "https://www.facebook.com/narendramodi/posts/10157222470805165:0", "name": "Comment"}, {"link": "https://www.facebook.com/narendramodi/posts/10157222470805165:0", "name": "Share"}], "updated_time": "2017-02-20T17:43:34+0000", "full_picture": "https://scontent.xx.fbcdn.net/v/t1.0-9/s720x720/13612183_10157222470805165_4418255001043724290_n.jpg?oh=8e0757b78808c7548fef14fb1d0edfd8&oe=5A06F076", "link": "https://www.facebook.com/narendramodi/photos/a.10150164299700165.421791.177526890164/10157222470805165/?type=3", "created_time": "2016-07-07T10:42:02+0000", "message": "A picture from the ceremonial welcome in Mozambique.", "type": "photo", "id": "177526890164_10157222470805165", "status_type": "added_photos"}