{"from": {"name": "Narendra Modi", "id": "177526890164"}, "actions": [{"link": "https://www.facebook.com/narendramodi/posts/10157928815975165:0", "name": "Like"}, {"link": "https://www.facebook.com/narendramodi/posts/10157928815975165:0", "name": "Comment"}, {"link": "https://www.facebook.com/narendramodi/posts/10157928815975165:0", "name": "Share"}], "updated_time": "2016-12-03T13:34:08+0000", "full_picture": "https://scontent.xx.fbcdn.net/v/t1.0-0/p480x480/15241757_10157928815975165_7824448034179879148_n.jpg?oh=06cc20b8f139ed9096f336f36f0ef847&oe=59CA3014", "link": "https://www.facebook.com/narendramodi/photos/a.10150164299700165.421791.177526890164/10157928815975165/?type=3", "created_time": "2016-12-03T13:34:08+0000", "message": "Reached Amritsar, where I will join the 'Heart of Asia' conference.", "type": "photo", "id": "177526890164_10157928815975165", "status_type": "added_photos"}