{"contributors": null, "truncated": false, "text": "Narendra Modi in Israel: The Apex of India\u2019s Diplomatic Realignment #rt https://t.co/Q0aNYrXNqa", "is_quote_status": false, "in_reply_to_status_id": null, "id": 882494966622294016, "favorite_count": 0, "entities": {"symbols": [], "user_mentions": [], "hashtags": [{"indices": [68, 71], "text": "rt"}], "urls": [], "media": [{"expanded_url": "https://twitter.com/GoldCoastBlog/status/882494966622294016/photo/1", "display_url": "pic.twitter.com/Q0aNYrXNqa", "url": "https://t.co/Q0aNYrXNqa", "media_url_https": "https://pbs.twimg.com/media/DD9AfoVWAAAaZDK.jpg", "id_str": "882494964134969344", "sizes": {"large": {"h": 523, "resize": "fit", "w": 700}, "small": {"h": 508, "resize": "fit", "w": 680}, "medium": {"h": 523, "resize": "fit", "w": 700}, "thumb": {"h": 150, "resize": "crop", "w": 150}}, "indices": [72, 95], "type": "photo", "id": 882494964134969344, "media_url": "http://pbs.twimg.com/media/DD9AfoVWAAAaZDK.jpg"}]}, "retweeted": false, "coordinates": null, "source": "<a href=\"https://ifttt.com\" rel=\"nofollow\">IFTTT</a>", "in_reply_to_screen_name": null, "in_reply_to_user_id": null, "retweet_count": 0, "id_str": "882494966622294016", "favorited": false, "user": {"follow_request_sent": false, "has_extended_profile": false, "profile_use_background_image": true, "default_profile_image": false, "id": 17750752, "profile_background_image_url_https": "https://pbs.twimg.com/profile_background_images/9113586/GoldCoastBlog.jpg", "verified": false, "translator_type": "none", "profile_text_color": "333333", "profile_image_url_https": "https://pbs.twimg.com/profile_images/146297862/GoldCoastBlog_normal.jpg", "profile_sidebar_fill_color": "FFFFFF", "entities": {"url": {"urls": [{"url": "https://t.co/XcxwCew08p", "indices": [0, 23], "expanded_url": "https://www.facebook.com/goldcoastblog", "display_url": "facebook.com/goldcoastblog"}]}, "description": {"urls": []}}, "followers_count": 2089, "profile_sidebar_border_color": "FFFFFF", "id_str": "17750752", "profile_background_color": "FFFFFF", "listed_count": 118, "is_translation_enabled": false, "utc_offset": 36000, "statuses_count": 61889, "description": "Gold Coast South East #Queensland Surfers Paradise Gold Coast - Local News, Storms \u2014 Breaking News From All Over The World", "friends_count": 933, "location": "Gold Coast Australia", "profile_link_color": "292727", "profile_image_url": "http://pbs.twimg.com/profile_images/146297862/GoldCoastBlog_normal.jpg", "following": false, "geo_enabled": false, "profile_banner_url": "https://pbs.twimg.com/profile_banners/17750752/1418107865", "profile_background_image_url": "http://pbs.twimg.com/profile_background_images/9113586/GoldCoastBlog.jpg", "screen_name": "GoldCoastBlog", "lang": "en", "profile_background_tile": false, "favourites_count": 123, "name": "Gold Coast Blog", "notifications": false, "url": "https://t.co/XcxwCew08p", "created_at": "Sun Nov 30 07:16:29 +0000 2008", "contributors_enabled": false, "time_zone": "Brisbane", "protected": false, "default_profile": false, "is_translator": false}, "geo": null, "in_reply_to_user_id_str": null, "possibly_sensitive": false, "lang": "en", "created_at": "Wed Jul 05 07:02:50 +0000 2017", "in_reply_to_status_id_str": null, "place": null, "extended_entities": {"media": [{"expanded_url": "https://twitter.com/GoldCoastBlog/status/882494966622294016/photo/1", "display_url": "pic.twitter.com/Q0aNYrXNqa", "url": "https://t.co/Q0aNYrXNqa", "media_url_https": "https://pbs.twimg.com/media/DD9AfoVWAAAaZDK.jpg", "id_str": "882494964134969344", "sizes": {"large": {"h": 523, "resize": "fit", "w": 700}, "small": {"h": 508, "resize": "fit", "w": 680}, "medium": {"h": 523, "resize": "fit", "w": 700}, "thumb": {"h": 150, "resize": "crop", "w": 150}}, "indices": [72, 95], "type": "photo", "id": 882494964134969344, "media_url": "http://pbs.twimg.com/media/DD9AfoVWAAAaZDK.jpg"}]}, "metadata": {"iso_language_code": "en", "result_type": "recent"}}