{"contributors": null, "truncated": false, "text": "RT @MEAIndiaShadow: Comparison of India's Relations with Israel and Palestine before Modi's visit #ModiInIsrael https://t.co/Q3ADzMMhM7", "is_quote_status": false, "in_reply_to_status_id": null, "id": 882494858362888192, "favorite_count": 0, "entities": {"symbols": [], "user_mentions": [{"id": 2782312248, "indices": [3, 18], "id_str": "2782312248", "screen_name": "MEAIndiaShadow", "name": "MEAIndiaShadow"}], "hashtags": [{"indices": [98, 111], "text": "ModiInIsrael"}], "urls": [], "media": [{"source_user_id": 2782312248, "source_status_id_str": "882494684387581952", "expanded_url": "https://twitter.com/MEAIndiaShadow/status/882494684387581952/photo/1", "display_url": "pic.twitter.com/Q3ADzMMhM7", "url": "https://t.co/Q3ADzMMhM7", "media_url_https": "https://pbs.twimg.com/media/DD9AJmUWsAIoOjL.jpg", "source_user_id_str": "2782312248", "source_status_id": 882494684387581952, "id_str": "882494585636827138", "sizes": {"small": {"h": 680, "resize": "fit", "w": 583}, "large": {"h": 2048, "resize": "fit", "w": 1755}, "medium": {"h": 1200, "resize": "fit", "w": 1028}, "thumb": {"h": 150, "resize": "crop", "w": 150}}, "indices": [112, 135], "type": "photo", "id": 882494585636827138, "media_url": "http://pbs.twimg.com/media/DD9AJmUWsAIoOjL.jpg"}]}, "retweeted": false, "coordinates": null, "source": "<a href=\"http://twitter.com\" rel=\"nofollow\">Twitter Web Client</a>", "in_reply_to_screen_name": null, "in_reply_to_user_id": null, "retweet_count": 1, "id_str": "882494858362888192", "favorited": false, "retweeted_status": {"contributors": null, "truncated": false, "text": "Comparison of India's Relations with Israel and Palestine before Modi's visit #ModiInIsrael https://t.co/Q3ADzMMhM7", "is_quote_status": false, "in_reply_to_status_id": null, "id": 882494684387581952, "favorite_count": 0, "entities": {"symbols": [], "user_mentions": [], "hashtags": [{"indices": [78, 91], "text": "ModiInIsrael"}], "urls": [], "media": [{"expanded_url": "https://twitter.com/MEAIndiaShadow/status/882494684387581952/photo/1", "display_url": "pic.twitter.com/Q3ADzMMhM7", "url": "https://t.co/Q3ADzMMhM7", "media_url_https": "https://pbs.twimg.com/media/DD9AJmUWsAIoOjL.jpg", "id_str": "882494585636827138", "sizes": {"small": {"h": 680, "resize": "fit", "w": 583}, "large": {"h": 2048, "resize": "fit", "w": 1755}, "medium": {"h": 1200, "resize": "fit", "w": 1028}, "thumb": {"h": 150, "resize": "crop", "w": 150}}, "indices": [92, 115], "type": "photo", "id": 882494585636827138, "media_url": "http://pbs.twimg.com/media/DD9AJmUWsAIoOjL.jpg"}]}, "retweeted": false, "coordinates": null, "source": "<a href=\"https://about.twitter.com/products/tweetdeck\" rel=\"nofollow\">TweetDeck</a>", "in_reply_to_screen_name": null, "in_reply_to_user_id": null, "retweet_count": 1, "id_str": "882494684387581952", "favorited": false, "user": {"follow_request_sent": false, "has_extended_profile": false, "profile_use_background_image": true, "default_profile_image": false, "id": 2782312248, "profile_background_image_url_https": "https://abs.twimg.com/images/themes/theme1/bg.png", "verified": false, "translator_type": "none", "profile_text_color": "333333", "profile_image_url_https": "https://pbs.twimg.com/profile_images/615391993456242688/vQEKFRjB_normal.jpg", "profile_sidebar_fill_color": "DDEEF6", "entities": {"description": {"urls": []}}, "followers_count": 5760, "profile_sidebar_border_color": "C0DEED", "id_str": "2782312248", "profile_background_color": "C0DEED", "listed_count": 47, "is_translation_enabled": false, "utc_offset": -25200, "statuses_count": 1791, "description": "This is the Shadow Handle of @MEAIndia  | This is an initiative to keep the government accountable based on constructive criticism.\nYour Voice | Our Pledge", "friends_count": 129, "location": "", "profile_link_color": "1DA1F2", "profile_image_url": "http://pbs.twimg.com/profile_images/615391993456242688/vQEKFRjB_normal.jpg", "following": false, "geo_enabled": false, "profile_banner_url": "https://pbs.twimg.com/profile_banners/2782312248/1435555841", "profile_background_image_url": "http://abs.twimg.com/images/themes/theme1/bg.png", "screen_name": "MEAIndiaShadow", "lang": "en", "profile_background_tile": false, "favourites_count": 76, "name": "MEAIndiaShadow", "notifications": false, "url": null, "created_at": "Sun Aug 31 14:06:16 +0000 2014", "contributors_enabled": false, "time_zone": "Pacific Time (US & Canada)", "protected": false, "default_profile": true, "is_translator": false}, "geo": null, "in_reply_to_user_id_str": null, "possibly_sensitive": false, "lang": "en", "created_at": "Wed Jul 05 07:01:43 +0000 2017", "in_reply_to_status_id_str": null, "place": null, "extended_entities": {"media": [{"expanded_url": "https://twitter.com/MEAIndiaShadow/status/882494684387581952/photo/1", "display_url": "pic.twitter.com/Q3ADzMMhM7", "url": "https://t.co/Q3ADzMMhM7", "media_url_https": "https://pbs.twimg.com/media/DD9AJmUWsAIoOjL.jpg", "id_str": "882494585636827138", "sizes": {"small": {"h": 680, "resize": "fit", "w": 583}, "large": {"h": 2048, "resize": "fit", "w": 1755}, "medium": {"h": 1200, "resize": "fit", "w": 1028}, "thumb": {"h": 150, "resize": "crop", "w": 150}}, "indices": [92, 115], "type": "photo", "id": 882494585636827138, "media_url": "http://pbs.twimg.com/media/DD9AJmUWsAIoOjL.jpg"}]}, "metadata": {"iso_language_code": "en", "result_type": "recent"}}, "user": {"follow_request_sent": false, "has_extended_profile": false, "profile_use_background_image": true, "default_profile_image": false, "id": 1139359566, "profile_background_image_url_https": "https://abs.twimg.com/images/themes/theme1/bg.png", "verified": false, "translator_type": "none", "profile_text_color": "333333", "profile_image_url_https": "https://pbs.twimg.com/profile_images/433725283468709888/44sqMCDX_normal.jpeg", "profile_sidebar_fill_color": "DDEEF6", "entities": {"description": {"urls": []}}, "followers_count": 251, "profile_sidebar_border_color": "C0DEED", "id_str": "1139359566", "profile_background_color": "C0DEED", "listed_count": 20, "is_translation_enabled": false, "utc_offset": -25200, "statuses_count": 18648, "description": "Research Student, CEG alumni, LFC & movies", "friends_count": 130, "location": "", "profile_link_color": "1DA1F2", "profile_image_url": "http://pbs.twimg.com/profile_images/433725283468709888/44sqMCDX_normal.jpeg", "following": false, "geo_enabled": false, "profile_banner_url": "https://pbs.twimg.com/profile_banners/1139359566/1494873353", "profile_background_image_url": "http://abs.twimg.com/images/themes/theme1/bg.png", "screen_name": "SELVA_BALAJI191", "lang": "en", "profile_background_tile": false, "favourites_count": 7324, "name": "SELVA BALAJI M", "notifications": false, "url": null, "created_at": "Fri Feb 01 11:08:07 +0000 2013", "contributors_enabled": false, "time_zone": "Pacific Time (US & Canada)", "protected": false, "default_profile": true, "is_translator": false}, "geo": null, "in_reply_to_user_id_str": null, "possibly_sensitive": false, "lang": "en", "created_at": "Wed Jul 05 07:02:24 +0000 2017", "in_reply_to_status_id_str": null, "place": null, "extended_entities": {"media": [{"source_user_id": 2782312248, "source_status_id_str": "882494684387581952", "expanded_url": "https://twitter.com/MEAIndiaShadow/status/882494684387581952/photo/1", "display_url": "pic.twitter.com/Q3ADzMMhM7", "url": "https://t.co/Q3ADzMMhM7", "media_url_https": "https://pbs.twimg.com/media/DD9AJmUWsAIoOjL.jpg", "source_user_id_str": "2782312248", "source_status_id": 882494684387581952, "id_str": "882494585636827138", "sizes": {"small": {"h": 680, "resize": "fit", "w": 583}, "large": {"h": 2048, "resize": "fit", "w": 1755}, "medium": {"h": 1200, "resize": "fit", "w": 1028}, "thumb": {"h": 150, "resize": "crop", "w": 150}}, "indices": [112, 135], "type": "photo", "id": 882494585636827138, "media_url": "http://pbs.twimg.com/media/DD9AJmUWsAIoOjL.jpg"}]}, "metadata": {"iso_language_code": "en", "result_type": "recent"}}